django_cache_otp/__init__.py
django_cache_otp/admin.py
django_cache_otp/apps.py
django_cache_otp/models.py
django_cache_otp/modules.py
django_cache_otp/otp.py
django_cache_otp/tests.py
django_cache_otp/views.py
django_cache_otp/migrations/__init__.py
django_cache_otp-0.2.2.dist-info/licenses/LICENSE
django_cache_otp-0.2.2.dist-info/METADATA
django_cache_otp-0.2.2.dist-info/WHEEL
django_cache_otp-0.2.2.dist-info/top_level.txt
django_cache_otp-0.2.2.dist-info/RECORD
