Metadata-Version: 2.4
Name: django-cache-otp
Version: 0.2.2
Summary: OTP system based on cache
Home-page: https://github.com/alijoghataee/django_cache_otp
Author: Ali Joghataee
Author-email: alijoghataee77@gmail.com
License: MIT
Project-URL: GitHub, https://github.com/alijoghataee/django_cache_otp
Classifier: Framework :: Django
Classifier: Programming Language :: Python :: 3
Classifier: License :: OSI Approved :: MIT License
License-File: LICENSE
Requires-Dist: django>=4.0
Requires-Dist: cryptography>=41.0.5
Dynamic: author
Dynamic: author-email
Dynamic: classifier
Dynamic: description
Dynamic: description-content-type
Dynamic: home-page
Dynamic: license
Dynamic: license-file
Dynamic: project-url
Dynamic: requires-dist
Dynamic: summary
